dmaikjsit/__init__.py
dmaikjsit/core.py
dmaikjsit/codes/Apriori_algo.ipynb
dmaikjsit/codes/DecisionTree_NaiveBayes.ipynb
dmaikjsit/codes/KMeans.ipynb
dmaikjsit/codes/Pre_Processing_On_Mixed_Attribute.ipynb
"dmaikjsit/codes/Statistical_Data_Analysis(Bining,chi-sqaure,correlation).ipynb"
dmaikjsit/codes/__init__.py
dmaikjsit-0.0.12.dist-info/METADATA
dmaikjsit-0.0.12.dist-info/WHEEL
dmaikjsit-0.0.12.dist-info/entry_points.txt
dmaikjsit-0.0.12.dist-info/top_level.txt
dmaikjsit-0.0.12.dist-info/RECORD
