Metadata-Version: 2.4
Name: dmaikjsit
Version: 0.0.12
Summary: It has all the Dmai codes
Author-email: Neel Parekh <neeluparekh001@gmail.com>
Classifier: Programming Language :: Python :: 3
Classifier: License :: OSI Approved :: MIT License
Classifier: Operating System :: OS Independent
Requires-Python: >=3.7
